Metadata-Version: 2.1
Name: odoo13-addon-ddmrp-adjustment
Version: 13.0.1.4.0
Summary: Allow to apply factor adjustments to buffers.
Home-page: https://github.com/OCA/ddmrp
Author: ForgeFlow, Odoo Community Association (OCA)
Author-email: support@odoo-community.org
License: AGPL-3
Platform: UNKNOWN
Classifier: Programming Language :: Python
Classifier: Framework :: Odoo
Classifier: Framework :: Odoo :: 13.0
Classifier: License :: OSI Approved :: GNU Affero General Public License v3
Classifier: Development Status :: 4 - Beta
Requires-Python: >=3.5
Requires-Dist: odoo13-addon-date-range
Requires-Dist: odoo13-addon-ddmrp
Requires-Dist: odoo13-addon-web-widget-x2many-2d-matrix
Requires-Dist: odoo <13.1dev,>=13.0a
